setup.cfg
setup.py
timecheckviz/__init__.py
timecheckviz/cmdline.py
timecheckviz.egg-info/PKG-INFO
timecheckviz.egg-info/SOURCES.txt
timecheckviz.egg-info/dependency_links.txt
timecheckviz.egg-info/entry_points.txt
timecheckviz.egg-info/requires.txt
timecheckviz.egg-info/top_level.txt
timecheckviz/analyzer/__init__.py
timecheckviz/analyzer/analyze.py
timecheckviz/commands/__init__.py
timecheckviz/commands/analyze.py