Metadata-Version: 1.1
Name: timecheckviz
Version: 0.0.1
Summary: Visualizer for timecheck
Home-page: https://github.com/arpitbbhayani/timecheckviz
Author: Arpit Bhayani
Author-email: arpit.b.bhayani@gmail.com
License: UNKNOWN
Download-URL: https://github.com/arpitbbhayani/timecheckviz
Keywords: time,metrics,visualizer,timecheck
Platform: UNKNOWN
